Workbook

Sheet Apresentação Gerencial
A1: 📊 APRESENTAÇÃO GERENCIAL | MATRIZ ORGANOGRAMA EXECUTIVA
A2: Análise Consolidada de Headcount | Agrícola + Manutenção Automotiva | Reduções Possível e Recomendada
A4: 1️⃣ RESUMO GERAL DO ORGANOGRAMA
A5: INDICADOR | B5: AGRÍCOLA | C5: MANUTENÇÃO | D5: TOTAL | E5: % TOTAL | G5: CRITICIDADE | H5: HC | I5: % TOTAL
A6: HC Total | B6: ='[1]Matriz Organograma'!R4 -> 754 | C6: ='[1]Matriz Organograma'!S4 -> 213 | D6: ='[1]Matriz Organograma'!T4 -> 967 | E6: =D6/D6 -> 1 | G6: 🟢 Crítica | H6: ='[1]Matriz Organograma'!J182 -> 732 | I6: =H6/$D$6 -> 0.75698035
A7: HC Crítico | B7: ='[1]Matriz Organograma'!R5 -> 568 | C7: ='[1]Matriz Organograma'!S5 -> 164 | D7: ='[1]Matriz Organograma'!T5 -> 732 | E7: =D7/D6 -> 0.75698035 | G7: 🟡 Alto | H7: ='[1]Matriz Organograma'!J183 -> 142 | I7: =H7/$D$6 -> 0.14684592
A8: HC Vinc. Equipamento | B8: ='[1]Matriz Organograma'!R6 -> 491 | C8: ='[1]Matriz Organograma'!S6 -> 163 | D8: ='[1]Matriz Organograma'!T6 -> 654 | E8: =D8/D6 -> 0.67631851 | G8: 🟠 Média | H8: ='[1]Matriz Organograma'!J184 -> 30 | I8: =H8/$D$6 -> 0.031023785
A9: Redução Possível | B9: ='[1]Matriz Organograma'!R7 -> 87 | C9: ='[1]Matriz Organograma'!S7 -> 18 | D9: ='[1]Matriz Organograma'!T7 -> 105 | E9: =D9/D6 -> 0.10858325 | G9: ⚪ Baixa | H9: ='[1]Matriz Organograma'!J185 -> 63 | I9: =H9/$D$6 -> 0.065149948
A10: Redução Recomendada | B10: 36 | C10: ='[1]Matriz Organograma'!S8 -> 5 | D10: 41 | E10: 4,2% | G10: TOTAL | H10: =SUM(H6:H9) -> 967 | I10: =H10/$D$6 -> 1
A11: HC Pós Redução Recom. | B11: 718 | C11: ='[1]Matriz Organograma'!S9 -> 208 | D11: 926 | E11: 95,8%
A13: 2️⃣ RESUMO POR SETOR E RESPONSÁVEL
A14: SETOR | B14: RESPONSÁVEL | C14: HC | D14: HC CRÍTICO | E14: HC VINC. EQUIP. | F14: RED. POSSÍVEL | G14: RED. RECOM. | H14: % HC
A15: Agrícola | B15: Flávio | C15: ='[1]Matriz Organograma'!C191 -> 243 | D15: ='[1]Matriz Organograma'!D191 -> 243 | E15: ='[1]Matriz Organograma'!E191 -> 202 | F15: ='[1]Matriz Organograma'!F191 -> 26 | G15: ='[1]Matriz Organograma'!G191 -> 7 | H15: =C15/$D$6 -> 0.25129266
A16: Agrícola | B16: Elias | C16: ='[1]Matriz Organograma'!C192 -> 182 | D16: ='[1]Matriz Organograma'!D192 -> 98 | E16: ='[1]Matriz Organograma'!E192 -> 98 | F16: ='[1]Matriz Organograma'!F192 -> 2 | G16: ='[1]Matriz Organograma'!G192 -> 2 | H16: =C16/$D$6 -> 0.18821096
A17: Agrícola | B17: Rogério | C17: ='[1]Matriz Organograma'!C193 -> 123 | D17: ='[1]Matriz Organograma'!D193 -> 87 | E17: ='[1]Matriz Organograma'!E193 -> 87 | F17: ='[1]Matriz Organograma'!F193 -> 19 | G17: ='[1]Matriz Organograma'!G193 -> 16 | H17: =C17/$D$6 -> 0.12719752
A18: Agrícola | B18: Ronaldo | C18: ='[1]Matriz Organograma'!C194 -> 120 | D18: ='[1]Matriz Organograma'!D194 -> 118 | E18: ='[1]Matriz Organograma'!E194 -> 84 | F18: ='[1]Matriz Organograma'!F194 -> 3 | G18: ='[1]Matriz Organograma'!G194 -> 1 | H18: =C18/$D$6 -> 0.12409514
A19: Agrícola | B19: Helena | C19: ='[1]Matriz Organograma'!C195 -> 34 | D19: ='[1]Matriz Organograma'!D195 -> 4 | E19: ='[1]Matriz Organograma'!E195 -> 2 | F19: ='[1]Matriz Organograma'!F195 -> 26 | G19: ='[1]Matriz Organograma'!G195 -> 1 | H19: =C19/$D$6 -> 0.03516029
A20: Agrícola | B20: Laércio | C20: ='[1]Matriz Organograma'!C196 -> 32 | D20: ='[1]Matriz Organograma'!D196 -> 18 | E20: ='[1]Matriz Organograma'!E196 -> 18 | F20: ='[1]Matriz Organograma'!F196 -> 9 | G20: ='[1]Matriz Organograma'!G196 -> 7 | H20: =C20/$D$6 -> 0.033092037
A21: Agrícola | B21: Pedro | C21: ='[1]Matriz Organograma'!C197 -> 12 | D21: ='[1]Matriz Organograma'!D197 -> 0 | E21: ='[1]Matriz Organograma'!E197 -> 0 | F21: ='[1]Matriz Organograma'!F197 -> 1 | G21: ='[1]Matriz Organograma'!G197 -> 1 | H21: =C21/$D$6 -> 0.012409514
A22: Agrícola | B22: Everton | C22: ='[1]Matriz Organograma'!C198 -> 7 | D22: ='[1]Matriz Organograma'!D198 -> 0 | E22: ='[1]Matriz Organograma'!E198 -> 0 | F22: ='[1]Matriz Organograma'!F198 -> 1 | G22: ='[1]Matriz Organograma'!G198 -> 1 | H22: =C22/$D$6 -> 0.0072388831
A23: Agrícola | B23: Devanir | C23: ='[1]Matriz Organograma'!C199 -> 1 | D23: ='[1]Matriz Organograma'!D199 -> 0 | E23: ='[1]Matriz Organograma'!E199 -> 0 | F23: ='[1]Matriz Organograma'!F199 -> 0 | G23: ='[1]Matriz Organograma'!G199 -> 0 | H23: =C23/$D$6 -> 0.0010341262
A24: Manutenção | B24: Paulo | C24: ='[1]Matriz Organograma'!C200 -> 76 | D24: ='[1]Matriz Organograma'!D200 -> 69 | E24: ='[1]Matriz Organograma'!E200 -> 66 | F24: ='[1]Matriz Organograma'!F200 -> 2 | G24: ='[1]Matriz Organograma'!G200 -> 0 | H24: =C24/$D$6 -> 0.078593588
A25: Manutenção | B25: Adriano | C25: ='[1]Matriz Organograma'!C201 -> 60 | D25: ='[1]Matriz Organograma'!D201 -> 33 | E25: ='[1]Matriz Organograma'!E201 -> 36 | F25: ='[1]Matriz Organograma'!F201 -> 9 | G25: ='[1]Matriz Organograma'!G201 -> 4 | H25: =C25/$D$6 -> 0.06204757
A26: Manutenção | B26: Hugo | C26: ='[1]Matriz Organograma'!C202 -> 50 | D26: ='[1]Matriz Organograma'!D202 -> 39 | E26: ='[1]Matriz Organograma'!E202 -> 39 | F26: ='[1]Matriz Organograma'!F202 -> 6 | G26: ='[1]Matriz Organograma'!G202 -> 1 | H26: =C26/$D$6 -> 0.051706308
A27: Manutenção | B27: Luiz Jr. | C27: ='[1]Matriz Organograma'!C203 -> 27 | D27: ='[1]Matriz Organograma'!D203 -> 23 | E27: ='[1]Matriz Organograma'!E203 -> 22 | F27: ='[1]Matriz Organograma'!F203 -> 1 | G27: ='[1]Matriz Organograma'!G203 -> 0 | H27: =C27/$D$6 -> 0.027921406
A28: TOTAL | B28: - | C28: =SUM(C15:C27) -> 967 | D28: =SUM(D15:D27) -> 732 | E28: =SUM(E15:E27) -> 654 | F28: =SUM(F15:F27) -> 105 | G28: =SUM(G15:G27) -> 41 | H28: =C28/$D$6 -> 1
A31: 3️⃣ RESUMO EXECUTIVO | REDUÇÃO POR FUNÇÃO
A32: FUNÇÃO | B32: HC TOTAL | C32: % HC | D32: RED. POSSÍVEL | E32: % POSS. | F32: RED. RECOM. | G32: % RECOM. | H32: OBS/JUSTIFICATIVA
A33: Coordenação | B33: 14 | C33: 1,4% | D33: 0 | E33: 0,0% | F33: 0 | G33: 0,0% | H33: Função estratégica - NÃO reduzir | K33: Função | L33: Possível | M33: Recomendada
A34: Gestor | B34: 7 | C34: 0,7% | D34: 2 | E34: 28,6% | F34: 0 | G34: 0,0% | H34: Gestão operacional crítica | K34: =A33 -> Coordenação | L34: =D33 -> 0 | M34: =F33 -> 0
A35: Trainee | B35: 3 | C35: 0,3% | D35: 3 | E35: 1 | F35: 2 | G35: 66,7% | H35: Formação de líderes - avaliar necessidade | K35: =A34 -> Gestor | L35: =D34 -> 2 | M35: =F34 -> 0
A36: Líder | B36: 68 | C36: 7,0% | D36: 18 | E36: 26,5% | F36: 13 | G36: 19,1% | H36: Supervisão direta - reduzir com cautela | K36: =A35 -> Trainee | L36: =D35 -> 3 | M36: =F35 -> 2
A37: Operador | B37: 287 | C37: 29,7% | D37: 32 | E37: 11,1% | F37: 0 | G37: 0,0% | H37: 🔒 PROTEGIDO - Operação direta equipamentos | K37: =A36 -> Líder | L37: =D36 -> 18 | M37: =F36 -> 13
A38: Motorista | B38: 89 | C38: 9,2% | D38: 8 | E38: 9,0% | F38: 0 | G38: 0,0% | H38: 🔒 PROTEGIDO - Logística essencial | K38: =A37 -> Operador | L38: =D37 -> 32 | M38: =F37 -> 0
A39: Mecânico | B39: 98 | C39: 10,1% | D39: 12 | E39: 12,2% | F39: 0 | G39: 0,0% | H39: 🔒 PROTEGIDO - Manutenção equipamentos | K39: =A38 -> Motorista | L39: =D38 -> 8 | M39: =F38 -> 0
A40: Eletricista | B40: 24 | C40: 2,5% | D40: 4 | E40: 16,7% | F40: 0 | G40: 0,0% | H40: 🔒 PROTEGIDO - Suporte elétrico crítico | K40: =A39 -> Mecânico | L40: =D39 -> 12 | M40: =F39 -> 0
A41: Auxiliar | B41: 42 | C41: 4,3% | D41: 8 | E41: 19,0% | F41: 9 | G41: 21,4% | H41: Apoio administrativo - pode otimizar | K41: =A40 -> Eletricista | L41: =D40 -> 4 | M41: =F40 -> 0
A42: Analista | B42: 12 | C42: 1,2% | D42: 4 | E42: 33,3% | F42: 4 | G42: 33,3% | H42: Funções analíticas - avaliar automação | K42: =A41 -> Auxiliar | L42: =D41 -> 8 | M42: =F41 -> 9
A43: Rurais | B43: 156 | C43: 16,1% | D43: 6 | E43: 3,8% | F43: 6 | G43: 3,8% | H43: Mão de obra direta campo | K43: =A42 -> Analista | L43: =D42 -> 4 | M43: =F42 -> 4
A44: Brigada | B44: 45 | C44: 4,7% | D44: 3 | E44: 6,7% | F44: 0 | G44: 0,0% | H44: 🔒 PROTEGIDO - Segurança/incêndio | K44: =A43 -> Rurais | L44: =D43 -> 6 | M44: =F43 -> 6
A45: Qualidade | B45: 34 | C45: 3,5% | D45: 0 | E45: 0,0% | F45: 0 | G45: 0,0% | H45: 🔒 PROTEGIDO - Controle qualidade | K45: =A44 -> Brigada | L45: =D44 -> 3 | M45: =F44 -> 0
A46: Outros | B46: 88 | C46: 9,1% | D46: 5 | E46: 5,7% | F46: 7 | G46: 8,0% | H46: Funções de suporte diversas | K46: =A45 -> Qualidade | L46: =D45 -> 0 | M46: =F45 -> 0
A47: TOTAL | B47: 967 | C47: 1 | D47: 105 | E47: 10,9% | F47: 41 | G47: 4,2% | K47: =A46 -> Outros | L47: =D46 -> 5 | M47: =F46 -> 7
A50: 4️⃣ RESUMO EXECUTIVO | REDUÇÃO POR RESPONSÁVEL (COM VALORES)
A51: RESPONSÁVEL | B51: SETOR | C51: HC TOTAL | D51: % HC | E51: RED. POSSÍVEL | F51: % POSS. | G51: RED. RECOM. | H51: % RECOM. | I51: OBS/JUSTIFICATIVA
A52: Flávio | B52: Agrícola | C52: 243 | D52: 25,1% | E52: 26 | F52: 24,8% | G52: 7 | H52: 17,1% | I52: Colheita/CTTA - função crítica
A53: Elias | B53: Agrícola | C53: 182 | D53: 18,8% | E53: 2 | F53: 1,9% | G53: 2 | H53: 4,9% | I53: Tratos/Herbicida - baixa redução
A54: Rogério | B54: Agrícola | C54: 123 | D54: 12,7% | E54: 19 | F54: 18,1% | G54: 16 | H54: 39,0% | I54: Preparo/Plantio - maior potencial
A55: Ronaldo | B55: Agrícola | C55: 120 | D55: 12,4% | E55: 3 | F55: 2,9% | G55: 1 | H55: 2,4% | I55: Fertirrigação - operação crítica
A56: Helena | B56: Agrícola | C56: 34 | D56: 3,5% | E56: 26 | F56: 24,8% | G56: 1 | H56: 2,4% | I56: Qualidade - função protegida
A57: Laércio | B57: Agrícola | C57: 32 | D57: 3,3% | E57: 9 | F57: 8,6% | G57: 7 | H57: 17,1% | I57: Irrigação - redução moderada
A58: Pedro | B58: Agrícola | C58: 12 | D58: 1,2% | E58: 1 | F58: 1,0% | G58: 1 | H58: 2,4% | I58: Apoio administrativo
A59: Everton | B59: Agrícola | C59: 7 | D59: 0,7% | E59: 1 | F59: 1,0% | G59: 1 | H59: 2,4% | I59: Apoio operacional
A60: Devanir | B60: Agrícola | C60: 1 | D60: 0,1% | E60: 0 | F60: 0,0% | G60: 0 | H60: 0,0% | I60: Parcerias - estratégico
A61: Paulo | B61: Manutenção | C61: 76 | D61: 7,9% | E61: 2 | F61: 1,9% | G61: 0 | H61: 0,0% | I61: Colheita manutenção - crítico
A62: Adriano | B62: Manutenção | C62: 60 | D62: 6,2% | E62: 9 | F62: 8,6% | G62: 4 | H62: 9,8% | I62: Apoio/Oficina - potencial moderado
A63: Hugo | B63: Manutenção | C63: 50 | D63: 5,2% | E63: 6 | F63: 5,7% | G63: 1 | H63: 2,4% | I63: Borracharia/Lubrificação
A64: Luiz Jr. | B64: Manutenção | C64: 27 | D64: 2,8% | E64: 1 | F64: 1,0% | G64: 0 | H64: 0,0% | I64: Tratos/Adubação - crítico
A65: TOTAL | B65: - | C65: 967 | D65: 1 | E65: 105 | F65: 1 | G65: 41 | H65: 1
A68: 5️⃣ RESUMO EXECUTIVO | REDUÇÃO POR FUNÇÃO (COM VALORES E %)
A69: FUNÇÃO | B69: HC TOTAL | C69: % HC | D69: RED. POSSÍVEL | E69: % POSS. | F69: RED. RECOM. | G69: % RECOM. | H69: SALÁRIO TOTAL | I69: INDENIZAÇÃO | J69: ECONOMIA ANUAL | K69: STATUS | L69: OBS/JUSTIFICATIVA
A70: Coordenação | B70: 14 | C70: 1,4% | D70: 0 | E70: 0,0% | F70: 0 | G70: 0,0% | H70: 0 | I70: 0 | J70: 0 | K70: 🔒 | L70: Função estratégica - NÃO reduzir
A71: Gestor | B71: 7 | C71: 0,7% | D71: 2 | E71: 1,9% | F71: 0 | G71: 0,0% | H71: =SUMIF('[1]Proposta de Redução HC'!E:E,"*Gestor*",'[1]Proposta de Redução HC'!F:F) -> 7704.22 | I71: =SUMIF('[1]Proposta de Redução HC'!E:E,"*Gestor*",'[1]Proposta de Redução HC'!G:G) -> 0 | J71: =SUMIF('[1]Proposta de Redução HC'!E:E,"*Gestor*",'[1]Proposta de Redução HC'!AA:AA) -> -121341.46 | K71: ⚠️ | L71: Gestão operacional crítica
A72: Trainee | B72: 3 | C72: 0,3% | D72: 3 | E72: 2,9% | F72: 2 | G72: 4,9% | H72: =SUMIF('[1]Proposta de Redução HC'!E:E,"*Trainee*",'[1]Proposta de Redução HC'!F:F) -> 17492.43 | I72: =SUMIF('[1]Proposta de Redução HC'!E:E,"*Trainee*",'[1]Proposta de Redução HC'!G:G) -> 32230.128 | J72: =SUMIF('[1]Proposta de Redução HC'!E:E,"*Trainee*",'[1]Proposta de Redução HC'!AA:AA) -> -219660.86 | K72: ✂️ | L72: Formação - avaliar necessidade
A73: Líder | B73: 68 | C73: 7,0% | D73: 18 | E73: 17,1% | F73: 13 | G73: 31,7% | H73: =SUMIF('[1]Proposta de Redução HC'!E:E,"*Lider*",'[1]Proposta de Redução HC'!F:F) -> 33358.09 | I73: =SUMIF('[1]Proposta de Redução HC'!E:E,"*Lider*",'[1]Proposta de Redução HC'!G:G) -> 214268.77 | J73: =SUMIF('[1]Proposta de Redução HC'!E:E,"*Lider*",'[1]Proposta de Redução HC'!AA:AA) -> -311121.15 | K73: ✂️ | L73: Supervisão - reduzir com cautela
A74: Operador | B74: 287 | C74: 29,7% | D74: 32 | E74: 30,5% | F74: 0 | G74: 0,0% | H74: =SUMIF('[1]Proposta de Redução HC'!E:E,"*Operador*",'[1]Proposta de Redução HC'!F:F) -> 23254.74 | I74: =SUMIF('[1]Proposta de Redução HC'!E:E,"*Operador*",'[1]Proposta de Redução HC'!G:G) -> 65915.352 | J74: =SUMIF('[1]Proposta de Redução HC'!E:E,"*Operador*",'[1]Proposta de Redução HC'!AA:AA) -> 0 | K74: 🔒 | L74: PROTEGIDO - Operação equipamentos
A75: Motorista | B75: 89 | C75: 9,2% | D75: 8 | E75: 7,6% | F75: 0 | G75: 0,0% | H75: =SUMIF('[1]Proposta de Redução HC'!E:E,"*Motorista*",'[1]Proposta de Redução HC'!F:F) -> 52609.89 | I75: =SUMIF('[1]Proposta de Redução HC'!E:E,"*Motorista*",'[1]Proposta de Redução HC'!G:G) -> 393029.56 | J75: =SUMIF('[1]Proposta de Redução HC'!E:E,"*Motorista*",'[1]Proposta de Redução HC'!AA:AA) -> 0 | K75: 🔒 | L75: PROTEGIDO - Logística essencial
A76: Mecânico | B76: 98 | C76: 10,1% | D76: 12 | E76: 11,4% | F76: 0 | G76: 0,0% | H76: =SUMIF('[1]Proposta de Redução HC'!E:E,"*Mec*",'[1]Proposta de Redução HC'!F:F) -> 43548.65 | I76: =SUMIF('[1]Proposta de Redução HC'!E:E,"*Mec*",'[1]Proposta de Redução HC'!G:G) -> 153559.32 | J76: =SUMIF('[1]Proposta de Redução HC'!E:E,"*Mec*",'[1]Proposta de Redução HC'!AA:AA) -> 0 | K76: 🔒 | L76: PROTEGIDO - Manutenção equipamentos
A77: Eletricista | B77: 24 | C77: 2,5% | D77: 4 | E77: 3,8% | F77: 0 | G77: 0,0% | H77: =SUMIF('[1]Proposta de Redução HC'!E:E,"*Eletr*",'[1]Proposta de Redução HC'!F:F) -> 0 | I77: =SUMIF('[1]Proposta de Redução HC'!E:E,"*Eletr*",'[1]Proposta de Redução HC'!G:G) -> 0 | J77: =SUMIF('[1]Proposta de Redução HC'!E:E,"*Eletr*",'[1]Proposta de Redução HC'!AA:AA) -> 0 | K77: 🔒 | L77: PROTEGIDO - Suporte elétrico crítico
A78: Auxiliar | B78: 42 | C78: 4,3% | D78: 8 | E78: 7,6% | F78: 9 | G78: 22,0% | H78: =SUMIF('[1]Proposta de Redução HC'!E:E,"*Auxiliar*",'[1]Proposta de Redução HC'!F:F) -> 55999 | I78: =SUMIF('[1]Proposta de Redução HC'!E:E,"*Auxiliar*",'[1]Proposta de Redução HC'!G:G) -> 210035.58 | J78: =SUMIF('[1]Proposta de Redução HC'!E:E,"*Auxiliar*",'[1]Proposta de Redução HC'!AA:AA) -> -643106.11 | K78: ✂️ | L78: Apoio administrativo - otimizar
A79: Analista | B79: 12 | C79: 1,2% | D79: 4 | E79: 3,8% | F79: 4 | G79: 9,8% | H79: =SUMIF('[1]Proposta de Redução HC'!E:E,"*Analista*",'[1]Proposta de Redução HC'!F:F) -> 8198.66 | I79: =SUMIF('[1]Proposta de Redução HC'!E:E,"*Analista*",'[1]Proposta de Redução HC'!G:G) -> 0 | J79: =SUMIF('[1]Proposta de Redução HC'!E:E,"*Analista*",'[1]Proposta de Redução HC'!AA:AA) -> -118060.7 | K79: ✂️ | L79: Funções analíticas - automação
A80: Rurais | B80: 156 | C80: 16,1% | D80: 6 | E80: 5,7% | F80: 6 | G80: 14,6% | H80: =SUMIF('[1]Proposta de Redução HC'!E:E,"*Rural*",'[1]Proposta de Redução HC'!F:F) -> 1688 | I80: =SUMIF('[1]Proposta de Redução HC'!E:E,"*Rural*",'[1]Proposta de Redução HC'!G:G) -> 0 | J80: =SUMIF('[1]Proposta de Redução HC'!E:E,"*Rural*",'[1]Proposta de Redução HC'!AA:AA) -> -477535.2 | K80: ✂️ | L80: Mão de obra direta campo
A81: Brigada | B81: 45 | C81: 4,7% | D81: 3 | E81: 2,9% | F81: 0 | G81: 0,0% | H81: =SUMIF('[1]Proposta de Redução HC'!E:E,"*Brigad*",'[1]Proposta de Redução HC'!F:F) -> 25353.9 | I81: =SUMIF('[1]Proposta de Redução HC'!E:E,"*Brigad*",'[1]Proposta de Redução HC'!G:G) -> 223229.12 | J81: =SUMIF('[1]Proposta de Redução HC'!E:E,"*Brigad*",'[1]Proposta de Redução HC'!AA:AA) -> 0 | K81: 🔒 | L81: PROTEGIDO - Segurança/incêndio
A82: Qualidade | B82: 34 | C82: 3,5% | D82: 0 | E82: 0,0% | F82: 0 | G82: 0,0% | H82: 0 | I82: 0 | J82: 0 | K82: 🔒 | L82: PROTEGIDO - Controle qualidade
A83: Outros | B83: 88 | C83: 9,1% | D83: 5 | E83: 4,8% | F83: 7 | G83: 17,1% | H83: =SUMIF('[1]Proposta de Redução HC'!E:E,"*Control*",'[1]Proposta de Redução HC'!F:F)+SUMIF('[1]Proposta de Redução HC'!E:E,"*Assistente*",'[1]Proposta de Redução HC'!F:F)+SUMIF('[1]Proposta de Redução HC'!E:E,"*Administrador*",'[1]Proposta de Redução HC'!F:F)+SUMIF('[1]Proposta de Redução HC'!E:E,"*Lavador*",'[1]Proposta de Redução HC'!F:F)+SUMIF('[1]Proposta de Redução HC'!E:E,"*Oficial*",'[1]Proposta de Redução HC'!F:F) -> 38388.81 | I83: =SUMIF('[1]Proposta de Redução HC'!E:E,"*Control*",'[1]Proposta de Redução HC'!G:G)+SUMIF('[1]Proposta de Redução HC'!E:E,"*Assistente*",'[1]Proposta de Redução HC'!G:G)+SUMIF('[1]Proposta de Redução HC'!E:E,"*Administrador*",'[1]Proposta de Redução HC'!G:G)+SUMIF('[1]Proposta de Redução HC'!E:E,"*Lavador*",'[1]Proposta de Redução HC'!G:G)+SUMIF('[1]Proposta de Redução HC'!E:E,"*Oficial*",'[1]Proposta de Redução HC'!G:G) -> 141952.25 | J83: =SUMIF('[1]Proposta de Redução HC'!E:E,"*Control*",'[1]Proposta de Redução HC'!AA:AA)+SUMIF('[1]Proposta de Redução HC'!E:E,"*Assistente*",'[1]Proposta de Redução HC'!AA:AA)+SUMIF('[1]Proposta de Redução HC'!E:E,"*Administrador*",'[1]Proposta de Redução HC'!AA:AA)+SUMIF('[1]Proposta de Redução HC'!E:E,"*Lavador*",'[1]Proposta de Redução HC'!AA:AA)+SUMIF('[1]Proposta de Redução HC'!E:E,"*Oficial*",'[1]Proposta de Redução HC'!AA:AA) -> -434561.89 | K83: ✂️ | L83: Funções de suporte diversas
A84: TOTAL | B84: =SUM(B70:B83) -> 967 | C84: 1 | D84: =SUM(D70:D83) -> 105 | E84: 1 | F84: =SUM(F70:F83) -> 41 | G84: 1 | H84: =SUM(H70:H83) -> 307596.39 | I84: =SUM(I70:I83) -> 1434220.1 | J84: ='[1]Proposta de Redução HC'!AA90 -> -3442598.8 | K84: -
A86: 📋 LEGENDA: 🔒 Função Protegida | ✂️ Redução Aprovada | ⚠️ Avaliar com cautela | ECONOMIA = Custo evitado (salário + encargos) - Indenização
A89: 6️⃣ PROPOSTA DE REDUÇÃO AGRÍCOLA E AUTOMOTIVA | CUSTOS, PRODUÇÃO E RECEITA
A90: Análise de Custos Evitados vs Impacto em Volume de Cana e Receita de Etanol
A92: ÁREA | B92: INICIATIVA | C92: CUSTOS EVITADOS | D92: HECTARES | E92: IMPACTO PROD. | F92: VOL. BAIXO | G92: VOL. MÉDIO | H92: VOL. ALTO | I92: RECEITA BAIXO | J92: RECEITA MÉDIO | K92: RECEITA ALTO | L92: OBS/JUSTIFICATIVA
A93: AGR | B93: BIOL MICROGEO | C93: ='[1]Proposta de Redução Agr e Aut.'!F3 -> 3223174.5 | D93: ='[1]Proposta de Redução Agr e Aut.'!J3 -> 15742 | E93: 2 a 4 t/ha | F93: ='[1]Proposta de Redução Agr e Aut.'!K3 -> 31484 | G93: ='[1]Proposta de Redução Agr e Aut.'!L3 -> 47226 | H93: ='[1]Proposta de Redução Agr e Aut.'!M3 -> 62968 | I93: ='[1]Proposta de Redução Agr e Aut.'!N3 -> 6649638.4 | J93: ='[1]Proposta de Redução Agr e Aut.'!O3 -> 9974457.6 | K93: ='[1]Proposta de Redução Agr e Aut.'!P3 -> 13299277 | L93: Menor risco - longo prazo
A94: AGR | B94: FERT UREIA PROTEGIDA | C94: ='[1]Proposta de Redução Agr e Aut.'!F4 -> 1609650 | D94: ='[1]Proposta de Redução Agr e Aut.'!J4 -> 4500 | E94: 1,5 a 6 t/ha | F94: ='[1]Proposta de Redução Agr e Aut.'!K4 -> 6750 | G94: ='[1]Proposta de Redução Agr e Aut.'!L4 -> 16875 | H94: ='[1]Proposta de Redução Agr e Aut.'!M4 -> 27000 | I94: ='[1]Proposta de Redução Agr e Aut.'!N4 -> 1425646.7 | J94: ='[1]Proposta de Redução Agr e Aut.'!O4 -> 3564116.6 | K94: ='[1]Proposta de Redução Agr e Aut.'!P4 -> 5702586.6 | L94: Subst. mineral por composto
A95: AGR | B95: CORR CALCÁRIO DOLOMÍTICO | C95: ='[1]Proposta de Redução Agr e Aut.'!F5 -> 1134000 | D95: ='[1]Proposta de Redução Agr e Aut.'!J5 -> 4200 | E95: 5 t/ha | F95: ='[1]Proposta de Redução Agr e Aut.'!K5 -> 7000 | G95: ='[1]Proposta de Redução Agr e Aut.'!L5 -> 14000 | H95: ='[1]Proposta de Redução Agr e Aut.'!M5 -> 21000 | I95: ='[1]Proposta de Redução Agr e Aut.'!N5 -> 1478448.4 | J95: ='[1]Proposta de Redução Agr e Aut.'!O5 -> 2956896.8 | K95: ='[1]Proposta de Redução Agr e Aut.'!P5 -> 4435345.2 | L95: Aplicação dobrada formação
A96: AGR | B96: CORR DOLOGESSO 70% | C96: ='[1]Proposta de Redução Agr e Aut.'!F6 -> 297894.45 | D96: ='[1]Proposta de Redução Agr e Aut.'!J6 -> 1124.13 | E96: 2 a 4 t/ha | F96: ='[1]Proposta de Redução Agr e Aut.'!K6 -> 3372.39 | G96: ='[1]Proposta de Redução Agr e Aut.'!L6 -> 4496.52 | H96: ='[1]Proposta de Redução Agr e Aut.'!M6 -> 5620.65 | I96: ='[1]Proposta de Redução Agr e Aut.'!N6 -> 712272.08 | J96: ='[1]Proposta de Redução Agr e Aut.'!O6 -> 949696.1 | K96: ='[1]Proposta de Redução Agr e Aut.'!P6 -> 1187120.1 | L96: Áreas baixo TCH
A97: AGR | B97: SERV. ENLEIRAMENTO | C97: ='[1]Proposta de Redução Agr e Aut.'!F7 -> 94704.814 | D97: ='[1]Proposta de Redução Agr e Aut.'!J7 -> 1412.24 | E97: 3 a 4 t/ha | F97: ='[1]Proposta de Redução Agr e Aut.'!K7 -> 4236.72 | G97: ='[1]Proposta de Redução Agr e Aut.'!L7 -> 4942.84 | H97: ='[1]Proposta de Redução Agr e Aut.'!M7 -> 5648.96 | I97: ='[1]Proposta de Redução Agr e Aut.'!N7 -> 894824.55 | J97: ='[1]Proposta de Redução Agr e Aut.'!O7 -> 1043962 | K97: ='[1]Proposta de Redução Agr e Aut.'!P7 -> 1193099.4 | L97: Risco cigarrinha
A98: AGR | B98: TRATOS SOQUEIRA (Consolidado) | C98: =SUM('[1]Proposta de Redução Agr e Aut.'!F8:F14) -> 1786390.1 | D98: 13900 | E98: 2-4 TCH / 1-2 ATR | F98: ='[1]Proposta de Redução Agr e Aut.'!K8 -> 41700 | G98: ='[1]Proposta de Redução Agr e Aut.'!L8 -> 55600 | H98: ='[1]Proposta de Redução Agr e Aut.'!M8 -> 69500 | I98: ='[1]Proposta de Redução Agr e Aut.'!N8 -> 8807328.2 | J98: ='[1]Proposta de Redução Agr e Aut.'!O8 -> 11743104 | K98: ='[1]Proposta de Redução Agr e Aut.'!P8 -> 14678880 | L98: Nemat+Biol+Micros
A99: AGR | B99: SERV. APLIC. FUNGICIDA | C99: ='[1]Proposta de Redução Agr e Aut.'!F15 -> 392000 | D99: ='[1]Proposta de Redução Agr e Aut.'!J15 -> 7000 | E99: 2 TCH | F99: ='[1]Proposta de Redução Agr e Aut.'!K15 -> 4666.6667 | G99: ='[1]Proposta de Redução Agr e Aut.'!L15 -> 9333.3333 | H99: ='[1]Proposta de Redução Agr e Aut.'!M15 -> 14000 | I99: ='[1]Proposta de Redução Agr e Aut.'!N15 -> 985632.26 | J99: ='[1]Proposta de Redução Agr e Aut.'!O15 -> 1971264.5 | K99: ='[1]Proposta de Redução Agr e Aut.'!P15 -> 2956896.8 | L99: Otimizada c/ Broca
A100: SUBTOTAL AGR (C/ IMPACTO PRODUÇÃO) | C100: =SUM(C93:C99) -> 8537813.9 | D100: - | E100: - | F100: =SUM(F93:F99) -> 99209.777 | G100: =SUM(G93:G99) -> 152473.69 | H100: =SUM(H93:H99) -> 205737.61 | I100: =SUM(I93:I99) -> 20953791 | J100: =SUM(J93:J99) -> 32203498 | K100: =SUM(K93:K99) -> 43453205
A102: REDUÇÕES SEM IMPACTO EM PRODUÇÃO
A103: ÁREA | B103: INICIATIVA | C103: CUSTOS EVITADOS | D103: OBS/JUSTIFICATIVA
A104: AGR | B104: Licença BI | C104: ='[1]Proposta de Redução Agr e Aut.'!F16 -> 5000
A105: AGR | B105: Retirar Despesas Viagens | C105: ='[1]Proposta de Redução Agr e Aut.'!F17 -> 120000
A106: AGR | B106: Reestruturação PCM | C106: ='[1]Proposta de Redução Agr e Aut.'!F18 -> 60000
A107: AGR | B107: Contrato Bene (Geotec) | C107: ='[1]Proposta de Redução Agr e Aut.'!F19 -> 26000 | D107: Manter valor 2025
A108: AGR | B108: Retirar licença RTX | C108: ='[1]Proposta de Redução Agr e Aut.'!F20 -> 20000
A109: AGR | B109: Redução IT pranchas | C109: ='[1]Proposta de Redução Agr e Aut.'!F21 -> 25000 | D109: Apenas 3 pranchas
A110: AGR | B110: Integração Solinftec | C110: ='[1]Proposta de Redução Agr e Aut.'!F22 -> 30000
A111: AGR | B111: Solinftec nuvem | C111: ='[1]Proposta de Redução Agr e Aut.'!F23 -> 184000
A112: AGR | B112: Licença FME (Topografia) | C112: ='[1]Proposta de Redução Agr e Aut.'!F24 -> 16000 | D112: Atualização 2 anos
A113: AGR | B113: Retirar km onibus Lay off | C113: ='[1]Proposta de Redução Agr e Aut.'!F25 -> 85000 | D113: Treinar na usina
...

Sheet 🎯 Dashboard
B2: DASHBOARD EXECUTIVO
B3: Reestruturação de Headcount & Custos | Agrícola + Manutenção Automotiva
B5: HEADCOUNT TOTAL | E5: REDUÇÃO RECOMENDADA | H5: ECONOMIA ANUAL RH | K5: CUSTOS EVITADOS — INICIATIVAS
B6: ='Apresentação Gerencial'!D6 -> 967 | E6: ='Apresentação Gerencial'!D10 -> 41 | H6: =-'Apresentação Gerencial'!J84 -> 3442598.8 | K6: ='Apresentação Gerencial'!C127 -> 10145966
B7: colaboradores (Agrícola + Manutenção) | E7: ='Apresentação Gerencial'!D10/'Apresentação Gerencial'!D6 -> 0.042399173 | H7: custo evitado líquido (salários − indenizações) | K7: agrícola + automotiva
B10: HEADCOUNT POR RESPONSÁVEL | H10: ECONOMIA ANUAL DE RH POR FUNÇÃO (R$)
B30: REDUÇÃO POR FUNÇÃO: POSSÍVEL vs RECOMENDADA | H30: COMPOSIÇÃO DO HEADCOUNT
B40: _dados: HC por responsável | E40: _dados: economia RH por função | H40: _dados: redução por função
B41: Responsável | C41: HC | E41: Função | F41: Economia (R$) | H41: Função | I41: Possível | J41: Recomendada
B42: ='Apresentação Gerencial'!A52 -> Flávio | C42: ='Apresentação Gerencial'!C52 -> 243 | E42: ='Apresentação Gerencial'!A70 -> Coordenação | F42: =-'Apresentação Gerencial'!J70 -> 0 | H42: ='Apresentação Gerencial'!A70 -> Coordenação | I42: ='Apresentação Gerencial'!D70 -> 0 | J42: ='Apresentação Gerencial'!F70 -> 0
B43: ='Apresentação Gerencial'!A53 -> Elias | C43: ='Apresentação Gerencial'!C53 -> 182 | E43: ='Apresentação Gerencial'!A71 -> Gestor | F43: =-'Apresentação Gerencial'!J71 -> 121341.46 | H43: ='Apresentação Gerencial'!A71 -> Gestor | I43: ='Apresentação Gerencial'!D71 -> 2 | J43: ='Apresentação Gerencial'!F71 -> 0
B44: ='Apresentação Gerencial'!A54 -> Rogério | C44: ='Apresentação Gerencial'!C54 -> 123 | E44: ='Apresentação Gerencial'!A72 -> Trainee | F44: =-'Apresentação Gerencial'!J72 -> 219660.86 | H44: ='Apresentação Gerencial'!A72 -> Trainee | I44: ='Apresentação Gerencial'!D72 -> 3 | J44: ='Apresentação Gerencial'!F72 -> 2
B45: ='Apresentação Gerencial'!A55 -> Ronaldo | C45: ='Apresentação Gerencial'!C55 -> 120 | E45: ='Apresentação Gerencial'!A73 -> Líder | F45: =-'Apresentação Gerencial'!J73 -> 311121.15 | H45: ='Apresentação Gerencial'!A73 -> Líder | I45: ='Apresentação Gerencial'!D73 -> 18 | J45: ='Apresentação Gerencial'!F73 -> 13
B46: ='Apresentação Gerencial'!A56 -> Helena | C46: ='Apresentação Gerencial'!C56 -> 34 | E46: ='Apresentação Gerencial'!A74 -> Operador | F46: =-'Apresentação Gerencial'!J74 -> 0 | H46: ='Apresentação Gerencial'!A74 -> Operador | I46: ='Apresentação Gerencial'!D74 -> 32 | J46: ='Apresentação Gerencial'!F74 -> 0
B47: ='Apresentação Gerencial'!A57 -> Laércio | C47: ='Apresentação Gerencial'!C57 -> 32 | E47: ='Apresentação Gerencial'!A75 -> Motorista | F47: =-'Apresentação Gerencial'!J75 -> 0 | H47: ='Apresentação Gerencial'!A75 -> Motorista | I47: ='Apresentação Gerencial'!D75 -> 8 | J47: ='Apresentação Gerencial'!F75 -> 0
B48: ='Apresentação Gerencial'!A58 -> Pedro | C48: ='Apresentação Gerencial'!C58 -> 12 | E48: ='Apresentação Gerencial'!A76 -> Mecânico | F48: =-'Apresentação Gerencial'!J76 -> 0 | H48: ='Apresentação Gerencial'!A76 -> Mecânico | I48: ='Apresentação Gerencial'!D76 -> 12 | J48: ='Apresentação Gerencial'!F76 -> 0
B49: ='Apresentação Gerencial'!A59 -> Everton | C49: ='Apresentação Gerencial'!C59 -> 7 | E49: ='Apresentação Gerencial'!A77 -> Eletricista | F49: =-'Apresentação Gerencial'!J77 -> 0 | H49: ='Apresentação Gerencial'!A77 -> Eletricista | I49: ='Apresentação Gerencial'!D77 -> 4 | J49: ='Apresentação Gerencial'!F77 -> 0
B50: ='Apresentação Gerencial'!A60 -> Devanir | C50: ='Apresentação Gerencial'!C60 -> 1 | E50: ='Apresentação Gerencial'!A78 -> Auxiliar | F50: =-'Apresentação Gerencial'!J78 -> 643106.11 | H50: ='Apresentação Gerencial'!A78 -> Auxiliar | I50: ='Apresentação Gerencial'!D78 -> 8 | J50: ='Apresentação Gerencial'!F78 -> 9
B51: ='Apresentação Gerencial'!A61 -> Paulo | C51: ='Apresentação Gerencial'!C61 -> 76 | E51: ='Apresentação Gerencial'!A79 -> Analista | F51: =-'Apresentação Gerencial'!J79 -> 118060.7 | H51: ='Apresentação Gerencial'!A79 -> Analista | I51: ='Apresentação Gerencial'!D79 -> 4 | J51: ='Apresentação Gerencial'!F79 -> 4
B52: ='Apresentação Gerencial'!A62 -> Adriano | C52: ='Apresentação Gerencial'!C62 -> 60 | E52: ='Apresentação Gerencial'!A80 -> Rurais | F52: =-'Apresentação Gerencial'!J80 -> 477535.2 | H52: ='Apresentação Gerencial'!A80 -> Rurais | I52: ='Apresentação Gerencial'!D80 -> 6 | J52: ='Apresentação Gerencial'!F80 -> 6
B53: ='Apresentação Gerencial'!A63 -> Hugo | C53: ='Apresentação Gerencial'!C63 -> 50 | E53: ='Apresentação Gerencial'!A81 -> Brigada | F53: =-'Apresentação Gerencial'!J81 -> 0 | H53: ='Apresentação Gerencial'!A81 -> Brigada | I53: ='Apresentação Gerencial'!D81 -> 3 | J53: ='Apresentação Gerencial'!F81 -> 0
B54: ='Apresentação Gerencial'!A64 -> Luiz Jr. | C54: ='Apresentação Gerencial'!C64 -> 27 | E54: ='Apresentação Gerencial'!A82 -> Qualidade | F54: =-'Apresentação Gerencial'!J82 -> 0 | H54: ='Apresentação Gerencial'!A82 -> Qualidade | I54: ='Apresentação Gerencial'!D82 -> 0 | J54: ='Apresentação Gerencial'!F82 -> 0
E55: ='Apresentação Gerencial'!A83 -> Outros | F55: =-'Apresentação Gerencial'!J83 -> 434561.89 | H55: ='Apresentação Gerencial'!A83 -> Outros | I55: ='Apresentação Gerencial'!D83 -> 5 | J55: ='Apresentação Gerencial'!F83 -> 7
E57: _comp HC
E58: Pós-redução recomendada | F58: ='Apresentação Gerencial'!D11 -> 926
E59: Redução recomendada | F59: ='Apresentação Gerencial'!D10 -> 41
E60: Redução adicional possível | F60: ='Apresentação Gerencial'!D9-'Apresentação Gerencial'!D10 -> 64

Sheet 📑 Resumo Diretoria
B2: RESUMO PARA DIRETORIA
B3: Reestruturação Agrícola + Manutenção Automotiva | Síntese e Recomendação
B5: CONTEXTO | E5: DECISÃO RECOMENDADA
B6: Análise consolidada de 967 colaboradores (754 Agrícola + 213 Manutenção). Do total, 732 são HC crítico (75,7%) e 654 estão vinculados a equipamentos. A proposta combina otimização de headcount com iniciativas agronômicas e automotivas de redução de custo. | E6: Aprovar a redução recomendada de 41 posições (4,2% do HC), preservando 100% das funções protegidas (Operador, Motorista, Mecânico, Eletricista, Brigada, Qualidade) ligadas à operação direta de equipamentos. Maior potencial concentrado em Rogério (16) e nas funções Líder e Auxiliar. Avançar com as iniciativas agronômicas e de frota em paralelo.
B8: IMPACTO FINANCEIRO CONSOLIDADO | E8: NÚMEROS-CHAVE DE HEADCOUNT
B9: Frente | C9: Valor Anual (R$) | D9: Tipo | E9: HC total | F9: ='Apresentação Gerencial'!D6 -> 967
B10: Economia anual de RH (líquida de indenizações) | C10: =-'Apresentação Gerencial'!J84 -> 3442598.8 | D10: Custo evitado | E10: HC crítico (75,7%) | F10: ='Apresentação Gerencial'!D7 -> 732
B11: Custos evitados — iniciativas agrícolas (c/ impacto produção) | C11: ='Apresentação Gerencial'!C100 -> 8537813.9 | D11: Custo evitado | E11: Vinculado a equipamento | F11: ='Apresentação Gerencial'!D8 -> 654
B12: Custos evitados — iniciativas agrícolas (sem impacto) | C12: ='Apresentação Gerencial'!C117 -> 1082000 | D12: Custo evitado | E12: Redução possível | F12: ='Apresentação Gerencial'!D9 -> 105
B13: Custos evitados — frota / automotiva | C13: ='Apresentação Gerencial'!C125 -> 526151.92 | D13: Custo evitado | E13: Redução recomendada | F13: ='Apresentação Gerencial'!D10 -> 41
B14: TOTAL ANUAL DE GANHO POTENCIAL | C14: =SUM(C10:C13) -> 13588565 | E14: HC pós-redução | F14: ='Apresentação Gerencial'!D11 -> 926
B16: NOTA — RECEITA PROTEGIDA
B17: As iniciativas agrícolas com impacto em produtividade sustentam um ganho estimado de receita de etanol entre R$ 21,0 mi (cenário baixo) e R$ 43,5 mi (cenário alto), com R$ 32,2 mi no cenário médio — além dos custos evitados acima. Os ganhos de produtividade (TCH/ATR) reforçam o retorno do programa para muito além da redução de despesa.
B19: Fonte: aba 'Apresentação Gerencial' | Reestruturação Umoe.xlsb. Valores anuais.

Sheet 🖥️ Deck Slides
B9: REESTRUTURAÇÃO 2025
B12: Agrícola + Manutenção Automotiva | Apresentação Gerencial Executiva
B15: Headcount • Redução de Custos • Receita Protegida
B22: 1. PANORAMA GERAL
C25: ='Apresentação Gerencial'!D6 -> 967 | F25: ='Apresentação Gerencial'!D10 -> 41 | J25: ='📑 Resumo Diretoria'!C10 -> 3442598.8 | N25: ='📑 Resumo Diretoria'!C14 -> 13588565
C26: Headcount total | F26: Redução recomendada (4,2%) | J26: Economia anual de RH | N26: Ganho total potencial/ano
C31: • 754 colaboradores na operação Agrícola e 213 na Manutenção Automotiva
C33: • 732 posições (75,7%) classificadas como HC crítico; 654 vinculadas a equipamentos
C35: • Redução possível de 105 posições; recomenda-se 41, preservando funções protegidas
C37: • Programa combina otimização de pessoas + iniciativas agronômicas e de frota
B42: 2. REDUÇÃO POR FUNÇÃO — POSSÍVEL vs RECOMENDADA
B62: 3. ECONOMIA DE RH POR FUNÇÃO (R$/ANO)
B82: 4. CUSTOS EVITADOS & RECEITA PROTEGIDA
B105: CONCLUSÃO & RECOMENDAÇÃO
B109: Aprovar 41 desligamentos recomendados (4,2%) + avançar com iniciativas agronômicas e de frota
B112: ='📑 Resumo Diretoria'!C14 -> 13588565
B116: + receita de etanol protegida estimada em R$ 32,2 mi/ano (cenário médio)
C123: Frente | D123: R$ | F123: Cenário receita etanol | G123: R$
C124: RH (líquido) | D124: ='📑 Resumo Diretoria'!C10 -> 3442598.8 | F124: Baixo | G124: ='Apresentação Gerencial'!I100 -> 20953791
C125: Agr c/ impacto | D125: ='📑 Resumo Diretoria'!C11 -> 8537813.9 | F125: Médio | G125: ='Apresentação Gerencial'!J100 -> 32203498
C126: Agr sem impacto | D126: ='📑 Resumo Diretoria'!C12 -> 1082000 | F126: Alto | G126: ='Apresentação Gerencial'!K100 -> 43453205
C127: Frota/Automotiva | D127: ='📑 Resumo Diretoria'!C13 -> 526151.92
